{
  "uuid": "1c1feba3-faff-4fad-808f-e5a581f72870",
  "lastMigration": 32,
  "name": "Tennis user",
  "endpointPrefix": "",
  "latency": 0,
  "port": 8080,
  "hostname": "",
  "folders": [],
  "routes": [
    {
      "uuid": "e4459978-6dcd-4f56-86c4-5a12274d7ee5",
      "type": "http",
      "documentation": "",
      "method": "get",
      "endpoint": "news",
      "responses": [
        {
          "uuid": "9155254b-cec2-4d9a-bb77-d399bb5cb5c1",
          "body": "{\n  \"data\": [\n    {\n      \"id\": 1,\n      \"image\": \"https://api-news.vba.vn/storage/images/1696931611_post%20web%202.jpg\",\n      \"title\": \"Vì sao bữa sáng là bữa quan trọng nhất trong ngày? Vì sao bữa sáng là bữa quan trọng nhất trong ngày?\",\n      \"createdAt\": \"2023-10-10T16:10:00.000Z\",\n      \"updatedAt\": \"2023-10-10T16:10:00.000Z\",\n      \"description\": \"Theo nhiều nghiên cứu về sức khỏe, bữa sáng là thời điểm bạn cung cấp cho cơ thể những nguồn năng lượng & dưỡng chất cho hầu hết các hoạt động sẽ diễn ra trong ngày; hay nói cách khác, bữa sáng chiếm 15% - 25% tổng năng lượng bạn cần nạp mỗi ngày....\"\n    },\n    {\n      \"id\": 2,\n      \"image\": \"https://api-news.vba.vn/storage/images/1696931611_post%20web%202.jpg\",\n      \"title\": \"Vì sao bữa sáng\",\n      \"createdAt\": \"2023-10-10T16:10:00.000Z\",\n      \"updatedAt\": \"2023-10-10T16:10:00.000Z\",\n      \"description\": \"Theo nhiều nghiên cứu về sức khỏe, bữa sáng là thời điểm bạn cung cấp cho cơ thể những nguồn năng lượng & dưỡng chất cho hầu hết các hoạt động sẽ diễn ra trong ngày; hay nói cách khác, bữa sáng chiếm 15% - 25% tổng năng lượng bạn cần nạp mỗi ngày....\"\n    },\n    {\n      \"id\": 3,\n      \"image\": \"https://api-news.vba.vn/storage/images/1696931611_post%20web%202.jpg\",\n      \"title\": \"Vì sao bữa sáng là bữa quan trọng nhất trong ngày?\",\n      \"createdAt\": \"2023-10-10T16:10:00.000Z\",\n      \"updatedAt\": \"2023-10-10T16:10:00.000Z\",\n      \"description\": \"Theo nhiều nghiên cứu về sức khỏe, bữa sáng là thời điểm bạn cung cấp cho cơ thể những nguồn năng lượng & dưỡng chất cho hầu hết các hoạt động sẽ diễn ra trong ngày; hay nói cách khác, bữa sáng chiếm 15% - 25% tổng năng lượng bạn cần nạp mỗi ngày....\"\n    },\n    {\n      \"id\": 4,\n      \"image\": \"http://api-news.vba.vn/storage/images/post%20web%202.jpg\",\n      \"title\": \"Vì sao bữa sáng là bữa quan trọng nhất trong ngày?\",\n      \"createdAt\": \"2023-10-10T16:10:00.000Z\",\n      \"updatedAt\": \"2023-10-10T16:10:00.000Z\",\n      \"description\": \"Theo nhiều nghiên cứu về sức khỏe, bữa sáng là thời điểm bạn cung cấp cho cơ thể những nguồn năng lượng & dưỡng chất cho hầu hết các hoạt động sẽ diễn ra trong ngày; hay nói cách khác, bữa sáng chiếm 15% - 25% tổng năng lượng bạn cần nạp mỗi ngày....\"\n    },\n    {\n      \"id\": 5,\n      \"image\": \"http://api-news.vba.vn/storage/images/post%20web%202.jpg\",\n      \"title\": \"Vì sao bữa sáng là bữa quan trọng nhất trong ngày?\",\n      \"createdAt\": \"2023-10-10T16:10:00.000Z\",\n      \"updatedAt\": \"2023-10-10T16:10:00.000Z\",\n      \"description\": \"Theo nhiều nghiên cứu về sức khỏe, bữa sáng là thời điểm bạn cung cấp cho cơ thể những nguồn năng lượng & dưỡng chất cho hầu hết các hoạt động sẽ diễn ra trong ngày; hay nói cách khác, bữa sáng chiếm 15% - 25% tổng năng lượng bạn cần nạp mỗi ngày....\"\n    },\n    {\n      \"id\": 6,\n      \"image\": \"https://api-news.vba.vn/storage/images/1696931611_post%20web%202.jpg\",\n      \"title\": \"Vì sao bữa sáng là bữa quan trọng nhất trong ngày?\",\n      \"createdAt\": \"2023-10-10T16:10:00.000Z\",\n      \"updatedAt\": \"2023-10-10T16:10:00.000Z\",\n      \"description\": \"Theo nhiều nghiên cứu về sức khỏe, bữa sáng là thời điểm bạn cung cấp cho cơ thể những nguồn năng lượng & dưỡng chất cho hầu hết các hoạt động sẽ diễn ra trong ngày; hay nói cách khác, bữa sáng chiếm 15% - 25% tổng năng lượng bạn cần nạp mỗi ngày....\"\n    },\n    {\n      \"id\": 7,\n      \"image\": \"https://api-news.vba.vn/storage/images/1696931611_post%20web%202.jpg\",\n      \"title\": \"Vì sao bữa sáng là bữa quan trọng nhất trong ngày?\",\n      \"createdAt\": \"2023-10-10T16:10:00.000Z\",\n      \"updatedAt\": \"2023-10-10T16:10:00.000Z\",\n      \"description\": \"Theo nhiều nghiên cứu về sức khỏe, bữa sáng là thời điểm bạn cung cấp cho cơ thể những nguồn năng lượng & dưỡng chất cho hầu hết các hoạt động sẽ diễn ra trong ngày; hay nói cách khác, bữa sáng chiếm 15% - 25% tổng năng lượng bạn cần nạp mỗi ngày....\"\n    },\n    {\n      \"id\": 8,\n      \"image\": \"https://api-news.vba.vn/storage/images/1696931611_post%20web%202.jpg\",\n      \"title\": \"Vì sao bữa sáng là bữa quan trọng nhất trong ngày?\",\n      \"createdAt\": \"2023-10-10T16:10:00.000Z\",\n      \"updatedAt\": \"2023-10-10T16:10:00.000Z\",\n      \"description\": \"Theo nhiều nghiên cứu về sức khỏe, bữa sáng là thời điểm bạn cung cấp cho cơ thể những nguồn năng lượng & dưỡng chất cho hầu hết các hoạt động sẽ diễn ra trong ngày; hay nói cách khác, bữa sáng chiếm 15% - 25% tổng năng lượng bạn cần nạp mỗi ngày....\"\n    },\n    {\n      \"id\": 9,\n      \"image\": \"https://api-news.vba.vn/storage/images/1696931611_post%20web%202.jpg\",\n      \"title\": \"Vì sao bữa sáng là bữa quan trọng nhất trong ngày?\",\n      \"createdAt\": \"2023-10-10T16:10:00.000Z\",\n      \"updatedAt\": \"2023-10-10T16:10:00.000Z\",\n      \"description\": \"Theo nhiều nghiên cứu về sức khỏe, bữa sáng là thời điểm bạn cung cấp cho cơ thể những nguồn năng lượng & dưỡng chất cho hầu hết các hoạt động sẽ diễn ra trong ngày; hay nói cách khác, bữa sáng chiếm 15% - 25% tổng năng lượng bạn cần nạp mỗi ngày....\"\n    },\n    {\n      \"id\": 10,\n      \"image\": \"https://api-news.vba.vn/storage/images/1696931611_post%20web%202.jpg\",\n      \"title\": \"Vì sao bữa sáng là bữa quan trọng nhất trong ngày?\",\n      \"createdAt\": \"2023-10-10T16:10:00.000Z\",\n      \"updatedAt\": \"2023-10-10T16:10:00.000Z\",\n      \"description\": \"Theo nhiều nghiên cứu về sức khỏe, bữa sáng là thời điểm bạn cung cấp cho cơ thể những nguồn năng lượng & dưỡng chất cho hầu hết các hoạt động sẽ diễn ra trong ngày; hay nói cách khác, bữa sáng chiếm 15% - 25% tổng năng lượng bạn cần nạp mỗi ngày....\"\n    },\n    {\n      \"id\": 11,\n      \"image\": \"https://api-news.vba.vn/storage/images/1696931611_post%20web%202.jpg\",\n      \"title\": \"Vì sao bữa sáng là bữa quan trọng nhất trong ngày?\",\n      \"createdAt\": \"2023-10-10T16:10:00.000Z\",\n      \"updatedAt\": \"2023-10-10T16:10:00.000Z\",\n      \"description\": \"Theo nhiều nghiên cứu về sức khỏe, bữa sáng là thời điểm bạn cung cấp cho cơ thể những nguồn năng lượng & dưỡng chất cho hầu hết các hoạt động sẽ diễn ra trong ngày; hay nói cách khác, bữa sáng chiếm 15% - 25% tổng năng lượng bạn cần nạp mỗi ngày....\"\n    },\n    {\n      \"id\": 12,\n      \"image\": \"https://api-news.vba.vn/storage/images/1696931611_post%20web%202.jpg\",\n      \"title\": \"Vì sao bữa sáng là bữa quan trọng nhất trong ngày?\",\n      \"createdAt\": \"2023-10-10T16:10:00.000Z\",\n      \"updatedAt\": \"2023-10-10T16:10:00.000Z\",\n      \"description\": \"Theo nhiều nghiên cứu về sức khỏe, bữa sáng là thời điểm bạn cung cấp cho cơ thể những nguồn năng lượng & dưỡng chất cho hầu hết các hoạt động sẽ diễn ra trong ngày; hay nói cách khác, bữa sáng chiếm 15% - 25% tổng năng lượng bạn cần nạp mỗi ngày....\"\n    }\n  ]\n}",
          "latency": 0,
          "statusCode": 200,
          "label": "",
          "headers": [],
          "bodyType": "INLINE",
          "filePath": "",
          "databucketID": "",
          "sendFileAsBody": false,
          "rules": [],
          "rulesOperator": "OR",
          "disableTemplating": false,
          "fallbackTo404": false,
          "default": true,
          "crudKey": "id",
          "callbacks": []
        }
      ],
      "responseMode": null
    },
    {
      "uuid": "c53b6246-fbbe-4962-b3a6-b256e1d6cbd2",
      "type": "http",
      "documentation": "",
      "method": "get",
      "endpoint": "news/top",
      "responses": [
        {
          "uuid": "67446c7f-a92f-43b0-bef5-f51b476033d5",
          "body": "{\n  \"data\": [\n    {\n      \"id\": 1,\n      \"image\": \"https://api-news.vba.vn/storage/images/1696931611_post%20web%202.jpg\",\n      \"title\": \"Vì sao bữa sáng là bữa quan trọng nhất trong ngày? Vì sao bữa sáng là bữa quan trọng nhất trong ngày?\",\n      \"createdAt\": \"2023-10-10T16:10:00.000Z\",\n      \"updatedAt\": \"2023-10-10T16:10:00.000Z\",\n      \"description\": \"Theo nhiều nghiên cứu về sức khỏe, bữa sáng là thời điểm bạn cung cấp cho cơ thể những nguồn năng lượng & dưỡng chất cho hầu hết các hoạt động sẽ diễn ra trong ngày; hay nói cách khác, bữa sáng chiếm 15% - 25% tổng năng lượng bạn cần nạp mỗi ngày....\"\n    },\n    {\n      \"id\": 2,\n      \"image\": \"https://api-news.vba.vn/storage/images/1696931611_post%20web%202.jpg\",\n      \"title\": \"Vì sao bữa sáng\",\n      \"createdAt\": \"2023-10-10T16:10:00.000Z\",\n      \"updatedAt\": \"2023-10-10T16:10:00.000Z\",\n      \"description\": \"Theo nhiều nghiên cứu về sức khỏe, bữa sáng là thời điểm bạn cung cấp cho cơ thể những nguồn năng lượng & dưỡng chất cho hầu hết các hoạt động sẽ diễn ra trong ngày; hay nói cách khác, bữa sáng chiếm 15% - 25% tổng năng lượng bạn cần nạp mỗi ngày....\"\n    },\n    {\n      \"id\": 3,\n      \"image\": \"https://api-news.vba.vn/storage/images/1696931611_post%20web%202.jpg\",\n      \"title\": \"Vì sao bữa sáng là bữa quan trọng nhất trong ngày?\",\n      \"createdAt\": \"2023-10-10T16:10:00.000Z\",\n      \"updatedAt\": \"2023-10-10T16:10:00.000Z\",\n      \"description\": \"Theo nhiều nghiên cứu về sức khỏe, bữa sáng là thời điểm bạn cung cấp cho cơ thể những nguồn năng lượng & dưỡng chất cho hầu hết các hoạt động sẽ diễn ra trong ngày; hay nói cách khác, bữa sáng chiếm 15% - 25% tổng năng lượng bạn cần nạp mỗi ngày....\"\n    },\n    {\n      \"id\": 4,\n      \"image\": \"https://api-news.vba.vn/storage/images/1696931611_post%20web%202.jpg\",\n      \"title\": \"Vì sao bữa sáng là bữa quan trọng nhất trong ngày?\",\n      \"createdAt\": \"2023-10-10T16:10:00.000Z\",\n      \"updatedAt\": \"2023-10-10T16:10:00.000Z\",\n      \"description\": \"Theo nhiều nghiên cứu về sức khỏe, bữa sáng là thời điểm bạn cung cấp cho cơ thể những nguồn năng lượng & dưỡng chất cho hầu hết các hoạt động sẽ diễn ra trong ngày; hay nói cách khác, bữa sáng chiếm 15% - 25% tổng năng lượng bạn cần nạp mỗi ngày....\"\n    },\n    {\n      \"id\": 5,\n      \"image\": \"https://api-news.vba.vn/storage/images/1696931611_post%20web%202.jpg\",\n      \"title\": \"Vì sao bữa sáng là bữa quan trọng nhất trong ngày?\",\n      \"createdAt\": \"2023-10-10T16:10:00.000Z\",\n      \"updatedAt\": \"2023-10-10T16:10:00.000Z\",\n      \"description\": \"Theo nhiều nghiên cứu về sức khỏe, bữa sáng là thời điểm bạn cung cấp cho cơ thể những nguồn năng lượng & dưỡng chất cho hầu hết các hoạt động sẽ diễn ra trong ngày; hay nói cách khác, bữa sáng chiếm 15% - 25% tổng năng lượng bạn cần nạp mỗi ngày....\"\n    }\n  ]\n}",
          "latency": 0,
          "statusCode": 200,
          "label": "",
          "headers": [],
          "bodyType": "INLINE",
          "filePath": "",
          "databucketID": "",
          "sendFileAsBody": false,
          "rules": [],
          "rulesOperator": "OR",
          "disableTemplating": false,
          "fallbackTo404": false,
          "default": true,
          "crudKey": "id",
          "callbacks": []
        }
      ],
      "responseMode": null
    }
  ],
  "rootChildren": [
    {
      "type": "route",
      "uuid": "e4459978-6dcd-4f56-86c4-5a12274d7ee5"
    },
    {
      "type": "route",
      "uuid": "c53b6246-fbbe-4962-b3a6-b256e1d6cbd2"
    }
  ],
  "proxyMode": false,
  "proxyHost": "",
  "proxyRemovePrefix": false,
  "tlsOptions": {
    "enabled": false,
    "type": "CERT",
    "pfxPath": "",
    "certPath": "",
    "keyPath": "",
    "caPath": "",
    "passphrase": ""
  },
  "cors": true,
  "headers": [
    {
      "key": "Content-Type",
      "value": "application/json"
    },
    {
      "key": "Access-Control-Allow-Origin",
      "value": "*"
    },
    {
      "key": "Access-Control-Allow-Methods",
      "value": "GET,POST,PUT,PATCH,DELETE,HEAD,OPTIONS"
    },
    {
      "key": "Access-Control-Allow-Headers",
      "value": "Content-Type, Origin, Accept, Authorization, Content-Length, X-Requested-With"
    }
  ],
  "proxyReqHeaders": [
    {
      "key": "",
      "value": ""
    }
  ],
  "proxyResHeaders": [
    {
      "key": "",
      "value": ""
    }
  ],
  "data": [],
  "callbacks": []
}